{
  "code": 1,
  "msg": "数据列表",
  "page": 1,
  "pagecount": 1,
  "limit": 20,
  "total": 1,
  "list": [
    {
      "vod_id": 1006,
      "vod_name": "高中数学(一数)",
      "vod_pic": "https://archive.biliimg.com/bfs/archive/3039bb79afad5ac816194b21f4f9942a23b4c46d.jpg",
      "vod_actor": "一数",
      "vod_director": "一数",
      "vod_des": "一个合集，所有高中数学内容！零基础与进阶学习全在这！每周两到三更，订阅后记得观看！",
      "vod_remarks": "159集",
      "vod_pubdate": "2020-02-26",
      "vod_year": "2020",
      "vod_area": "中国大陆",
      "vod_lang": "汉语普通话",
      "vod_play_from": "BiLiBiLi",
      "vod_play_url": "分P大合集形式|可按照自己喜爱的方式观看分P大合集形式或者单独视频组成合集形式$https://www.bilibili.com/video/BV147411K7xu#高中数学「最全」大合集预告！$https://www.bilibili.com/video/BV1AM4y1j77u#【初高衔接】上高中前，你需要知道的“等式变形”技巧都在这！$https://www.bilibili.com/video/BV1p14y1d7PV#【初高衔接】奇形怪状的“不等式”怎么解？一个视频搞定！$https://www.bilibili.com/video/BV1bc411c73k#【初高衔接】根的分布问题——高中没细讲，初中没学过$https://www.bilibili.com/video/BV1fX4y1L7ih#【集合|基础知识】集合的概念（易）$https://www.bilibili.com/video/BV11P411s7dd#【集合|基础知识】集合间关系（易）$https://www.bilibili.com/video/BV1Lp4y1E7ir#【集合 | 基础知识】集合的运算（易）$https://www.bilibili.com/video/BV15a411A73y#【集合 | 常考模型】集合“月考必考”大题 （中档）$https://www.bilibili.com/video/BV1ky4y1k76e#【集合 | 常考模型】集合易错大盘点（中档）$https://www.bilibili.com/video/BV1ch4y1v7VE#【集合 | 云刷题课】集合新定义问题（中档）$https://www.bilibili.com/video/BV1Gk4y1z7em#【逻辑 | 基础知识】充分必要条件和全称存在量词（易）$https://www.bilibili.com/video/BV1NN411H79R#【不等式 | 基础知识】不等式的简单性质$https://www.bilibili.com/video/BV1VQ4y1o7Dw#【不等式 | 基础知识】基本不等式（中档）$https://www.bilibili.com/video/BV1Qp4y1w7Fw#【不等式 | 常考模型】基本不等式「进阶方法」全梳理！$https://www.bilibili.com/video/BV13C4y1o76F#【不等式 | 基础知识】二次函数与不等式$https://www.bilibili.com/video/BV13t411E7Nn#【函数|基础知识】函数的概念（易）$https://www.bilibili.com/video/BV1o841117AL#【函数|常考模型】 函数三要素（易）$https://www.bilibili.com/video/BV16Q4y1W7ZK#【函数|常考模型】分式函数求值域（中档）$https://www.bilibili.com/video/BV1dv411y7cd#【高一】恒成立不会做？分类讨论+必要探路+分离参数！$https://www.bilibili.com/video/BV1bXC9YJE9c#【函数|基础知识】函数的单调性（易）$https://www.bilibili.com/video/BV1Ca4y1s7yB#“同增异减”是什么？复合函数单调性梳理！$https://www.bilibili.com/video/BV1bNyRBCEFd#【函数|基础知识】函数的奇偶性（易）$https://www.bilibili.com/video/BV1ev411775j#【函数|常考模型】单调性奇偶性复习$https://www.bilibili.com/video/BV1xk1WYaEkw#【函数|常考模型】函数的对称性与周期性$https://www.bilibili.com/video/BV1hnSdY6Ev4#「抽象函数」性质大综合问题！$https://www.bilibili.com/video/BV1BWDBYBEnT#【函数|常考模型】抽象函数+恒成立+构造函数（拔高）$https://www.bilibili.com/video/BV12h4y1i7Bv#【函数|基础知识】幂函数的图象与性质（易）$https://www.bilibili.com/video/BV1xv411L77D#【函数|基础知识】指数与运算性质（易）$https://www.bilibili.com/video/BV1Bp4y1t7S3#【函数|基础知识】指数函数（易）$https://www.bilibili.com/video/BV1LU4y1h7z5#指数函数+幂函数，重点难点全梳理！$https://www.bilibili.com/video/BV16f1mB7EHa#【函数|基础知识】对数运算（中档）$https://www.bilibili.com/video/BV1HG41197X4#【函数|基础知识】对数函数（中档）$https://www.bilibili.com/video/BV1Gh411D7vY#【高一必看】比大小！技巧全梳理！$https://www.bilibili.com/video/BV1xmSKBEEwz#【函数|常考模型】指对函数的“灵活考法” (中档)$https://www.bilibili.com/video/BV15UBiYhE5a#【函数|常考模型】指对幂复杂函数串讲（进阶）$https://www.bilibili.com/video/BV1Lc411X7YT#【函数|基础知识】函数的零点（易）$https://www.bilibili.com/video/BV1tY411J77h#【函数】函数解题思路梳理（进阶）$https://www.bilibili.com/video/BV1nu4y1P7TL#【函数|云刷题】函数复习课（进阶）$https://www.bilibili.com/video/BV1Jw411n78C#【三角函数|基础知识】任意角（易）$https://www.bilibili.com/video/BV12B4y1K7Fa#【三角函数|基础知识】弧度制（易）$https://www.bilibili.com/video/BV1FA41137gu#【三角函数|基础知识】弧长与面积（易）$https://www.bilibili.com/video/BV1R64y167qG#【三角函数|基础知识】三角函数概念（中档）$https://www.bilibili.com/video/BV1KC4y1A7vC#【三角函数｜基础知识】诱导公式（中档）$https://www.bilibili.com/video/BV1GN41177c8#【三角函数|基础知识】sinx/cosx/tanx图象与性质（中档）$https://www.bilibili.com/video/BV1F64y1L7tL#【三角函数|常考模型】三角函数小技巧（中档）$https://www.bilibili.com/video/BV1oj411p7ws#【三角函数 | 常考模型】“Asin(⍵x+φ)+B”的第一课：平移伸缩变换（易）$https://www.bilibili.com/video/BV18A411u7eZ#【三角函数 | 常考模型】“Asin(⍵x+φ)+B”的第二课：参数含义$https://www.bilibili.com/video/BV1rV411o75s#【三角函数 | 常考模型】“Asin(⍵x+φ)+B”的第三课：整体代换$https://www.bilibili.com/video/BV1fE411A7iz#【三角函数 | 常考模型】“Asin(⍵x+φ)+B”的第四课：几何法（拔高）$https://www.bilibili.com/video/BV1RN4y1x7D2#【三角函数|基础知识】sin与cos的两角和差公式（易）$https://www.bilibili.com/video/BV1eb4y1k7RX#【三角函数|基础知识】tan的两角和差公式（易）$https://www.bilibili.com/video/BV1Zh411h7qJ#【三角函数|常考模型】两角和差公式解题方法大串讲（进阶）$https://www.bilibili.com/video/BV1FB4y1T7Lc#【三角函数|基础知识】二倍角公式的基础应用（易）$https://www.bilibili.com/video/BV1mq4y1s7pz#三角函数𝜔取值范围大串讲！$https://www.bilibili.com/video/BV1qJwKe3Ey5#【三角函数|常考题型】二倍角公式的常见变形（中档）$https://www.bilibili.com/video/BV1iq4y1s75g#【三角函数|常考模型】二倍角公式的进阶方法（中档）$https://www.bilibili.com/video/BV1hh411B7Vx#【三角函数|基础知识】辅助角公式（中档）$https://www.bilibili.com/video/BV1T64y1s7YX#【三角函数|基础知识】和差化积与积化和差（选学）$https://www.bilibili.com/video/BV1144y117S2#【三角函数|常考模型】恒等变换大梳理（中档）$https://www.bilibili.com/video/BV1pe411q79E#三角恒等变换不会做题？30分钟学会思路！$https://www.bilibili.com/video/BV1hyCbYmEsp#高一期末想考高分，这些考点需要掌握！$https://www.bilibili.com/video/BV1F64y1T7FQ#开学要学平面向量？一个视频基础通关！$https://www.bilibili.com/video/BV1eC411W7L3#平面向量不会做题？画图法+三点共线定理+等和线！重要技巧大梳理！$https://www.bilibili.com/video/BV1mJ4m1e7FQ#平面向量的数量积（基础）$https://www.bilibili.com/video/BV1JU4y1H7rg#数量积没思路？投影+拆解+极化恒等式 ！一步到位！$https://www.bilibili.com/video/BV1RH4y157t9#平面向量基本定理（基础）$https://www.bilibili.com/video/BV13K4y1Q7jP#平面向量的坐标运算（基础）$https://www.bilibili.com/video/BV1A4411X7rV#【平面向量】无计可施？马上建系！$https://www.bilibili.com/video/BV13J4m187TJ#2025 平面向量必会十题【技巧篇】$https://www.bilibili.com/video/BV1brQyY5Eo7#【必做十题】平面向量不会翻译？来学技巧！$https://www.bilibili.com/video/BV1BTXkYXEjK#【解三角形】正余弦定理（基础）$https://www.bilibili.com/video/BV1gt411j7Zh#【解三角形|常考题型】三角形解的个数&测量问题（基础）$https://www.bilibili.com/video/BV1Et411j7qJ#【解三角形|常考题型】边角化简（中档）$https://www.bilibili.com/video/BV1Pt411N7gL#【解三角形|常考题型】最值与范围（进阶）$https://www.bilibili.com/video/BV1kt411M7YF#遇见多三角形，如何解？【正余弦定理进阶】$https://www.bilibili.com/video/BV1xA4m1N7oB#立体几何第一课！空间几何体$https://www.bilibili.com/video/BV1YgzTBTEGf#【立体几何】斜二测画法$https://www.bilibili.com/video/BV1qt411P7Kx#【立体几何】柱体、锥体、台体的体积问题$https://www.bilibili.com/video/BV1fY61BZEm8#祖暅原理与球的体积表面积！立体几何零基础讲解！$https://www.bilibili.com/video/BV1xEFWztE16#【立体几何】空间中的点线面$https://www.bilibili.com/video/BV1m4411X7Yf#【立体几何】空间中的平行$https://www.bilibili.com/video/BV1Qt411N7J3#“平行证明”不会连辅助线？一个视频讲懂！$https://www.bilibili.com/video/BV1uF4m1P7DK#【立体几何】空间中的垂直$https://www.bilibili.com/video/BV1Wt411u7je#立体几何垂直证明！保姆级梳理！$https://www.bilibili.com/video/BV18J3RzEERW#【立体几何】垂直不会做？技巧全在这！$https://www.bilibili.com/video/BV1wqMfzrEvT#“空间角度”不会“几何法”？保姆级教程在此！$https://www.bilibili.com/video/BV1rM4m117rL#「空间角」有“动点”就懵了？几何法来啦！$https://www.bilibili.com/video/BV1nw4m1k7ox#【空间向量】空间向量及其运算（易）$https://www.bilibili.com/video/BV1Bj411i7ML#【空间向量】空间向量的坐标运算$https://www.bilibili.com/video/BV19f4y117hk#【空间向量】证明平行与垂直（中档）$https://www.bilibili.com/video/BV1bN411p7va#【空间向量】空间中的角度（中档）$https://www.bilibili.com/video/BV1WT4y1M7p9#【空间向量】空间中的距离问题（中档）$https://www.bilibili.com/video/BV1s64y1F7jE#立体几何「不好建系」「不好求坐标」怎么办？$https://www.bilibili.com/video/BV1vX4Ce6Ecy#【立体几何必会十题】赛博刷题！专治不会！上篇$https://www.bilibili.com/video/BV1XWWNzyEeW#挑战高考历年最难「立体几何」大题！$https://www.bilibili.com/video/BV1rptrejEfK#【直线第一课】看似“简单”却“坑点满满”的直线大总结！| 高中数学大合集$https://www.bilibili.com/video/BV1eF41197v2#【直线第二课】一个视频搞懂“求直线”的所有方法！| 高中数学大合集$https://www.bilibili.com/video/BV1814y1Q7CP#【直线第三课】交点坐标与距离公式（中档）$https://www.bilibili.com/video/BV1G44y16761#【直线和圆 | 基础知识】圆的标准方程（易）$https://www.bilibili.com/video/BV1Ef421B7PJ#【直线和圆 | 基础知识】圆的一般方程（易）$https://www.bilibili.com/video/BV1Cf4y197Sn#【直线和圆】直线和圆的位置关系（中档）$https://www.bilibili.com/video/BV1Z4411z7P6#【直线和圆】圆与圆的位置关系（中档）$https://www.bilibili.com/video/BV1xt411F7Np#「直线和圆」最值模型大梳理！保姆级讲解！$https://www.bilibili.com/video/BV1Wk4weTEpK#【直线和圆进阶】数形结合+参数方程！$https://www.bilibili.com/video/BV1NZn7zFEQk#直线和圆大热点！切线+隐圆阿氏圆！$https://www.bilibili.com/video/BV1NGxxzhEka#【圆锥曲线|基础知识】椭圆的定义与标准方程（易）$https://www.bilibili.com/video/BV1qu4y1s7At#【圆锥曲线|常考模型】椭圆核心题型（中档）$https://www.bilibili.com/video/BV1be411R7uE#「椭圆离心率」无从下手？来学出题思路！$https://www.bilibili.com/video/BV1chytYaE4C#“离心率”一问范围就发懵？技巧在此！$https://www.bilibili.com/video/BV1BZhEz5Esd#「椭圆大题」一小时零基础上手！初学者必看！$https://www.bilibili.com/video/BV1gSavzUEUK#双曲线的标准方程【基础】$https://www.bilibili.com/video/BV1Et411j72N#双曲线的几何性质【基础】$https://www.bilibili.com/video/BV13t411j7Fd#「双曲线」不会数形结合？一个视频搞定！$https://www.bilibili.com/video/BV15y1pY3EAD#直线与双曲线！保姆级讲解$https://www.bilibili.com/video/BV1F615BpErW#抛物线的标准方程【基础】$https://www.bilibili.com/video/BV1Ct411w7x1#高考中出现的“抛物线”二级结论！$https://www.bilibili.com/video/BV14WDAYQEyy#【圆锥曲线|常考模型】压轴大题方法论（中档）$https://www.bilibili.com/video/BV1w94y157Ti#【圆锥曲线|常考模型】弦长面积问题（进阶）$https://www.bilibili.com/video/BV1MH4y167ui#圆锥曲线！定点问题！$https://www.bilibili.com/video/BV1NeDrYtEQ3#圆锥曲线！切线问题！$https://www.bilibili.com/video/BV1NtUeYYET5#【圆锥曲线】条件翻译大总结！专治没有思路！$https://www.bilibili.com/video/BV1Uu411F7Xs#圆锥曲线“二级结论”太多啦！先学这些最常考的！$https://www.bilibili.com/video/BV1qH4y1B7dm#还没动笔，居然能看出答案！【圆锥曲线模型盘点】$https://www.bilibili.com/video/BV1oN4y1m7ww#「阿基米德三角形」保姆级讲解！$https://www.bilibili.com/video/BV1Tw4m1Z72q#【数列| | 基础知识】什么是数列？$https://www.bilibili.com/video/BV1Qt411u7eL#【数列 | 基础知识】等差数列和基本公式$https://www.bilibili.com/video/BV16t411T766#「等差数列」重点全在这！公式+二级结论+变形！$https://www.bilibili.com/video/BV1KN4y1e7S5#等比数列，从基础到进阶！$https://www.bilibili.com/video/BV1iN411j7qT#【数列】等差等比一课通！公式+结论+高考大题！$https://www.bilibili.com/video/BV1F5BGYiE8t#【数列求和串讲】错位相减+裂项相消+分组求和！$https://www.bilibili.com/video/BV1f6kbY4EaG#高考必考「数列求通项」方法大总结！$https://www.bilibili.com/video/BV1E4c4ePEJT#【数列常考】遇见“奇偶讨论”就害怕？看我搞定！$https://www.bilibili.com/video/BV1D5iFBzE67#数列必做十题「上篇」$https://www.bilibili.com/video/BV1ycwPe1Esb#数列必做十题「最值+奇偶+花式讨论」$https://www.bilibili.com/video/BV1fqfnY5EQy#数列必做十题「压轴终篇」$https://www.bilibili.com/video/BV15DP9eVEkL#【导数|基础知识】导数的概念（易）$https://www.bilibili.com/video/BV1iZ421y71z#【导数 | 常考模型】导数与切线（中档）$https://www.bilibili.com/video/BV1sx42127hu#【导数 | 常考模型】导数、单调性、与极值（中档）$https://www.bilibili.com/video/BV1im411d7Eu#【导数必学】求导后无从下手？三个思路轻松搞定！$https://www.bilibili.com/video/BV1b1XXYqEk2#「导数含参单调性讨论」一小时大串讲！$https://www.bilibili.com/video/BV1Ev9QYJEpB#导数与不等式证明！直接求导+变换主元！$https://www.bilibili.com/video/BV1uAZjBBEsj#导数恒成立问题！分离参数与分类讨论！保姆级讲解$https://www.bilibili.com/video/BV1VafCB4EL1#【导数恒成立】数形结合+双变量必会题型！奶妈级讲解！$https://www.bilibili.com/video/BV1mcPMzbEvK#【导数 | 常考模型】隐零点问题（进阶）$https://www.bilibili.com/video/BV19K421v7zB#【导数 | 常考模型】导数放缩技巧第一课（中档）$https://www.bilibili.com/video/BV1h4421U7fj#导数！放缩！进阶！$https://www.bilibili.com/video/BV1mi42167aL#【导数 | 常考模型】恒成立问题之“端点效应”（进阶）$https://www.bilibili.com/video/BV1rw4m1e7tC#【导数 | 常考模型】端点效应失效怎么办（进阶）$https://www.bilibili.com/video/BV1Br4y1Q7ay#【必要探路法】导数不能不学的方法！$https://www.bilibili.com/video/BV1CswszFEYm#高考大热点！同构第一课！$https://www.bilibili.com/video/BV17yAPegEYd#导数与「指对同构」保姆级讲解$https://www.bilibili.com/video/BV1x4AmerECq#【导数热门】零点与找点！姥姥级串讲！$https://www.bilibili.com/video/BV14VXCYBEFR#导数常客：极值点偏移问题，一个视频讲懂！$https://www.bilibili.com/video/BV1K4421f7zT#【导数进阶】极值点偏移？齐次消元+比值代换！$https://www.bilibili.com/video/BV1bZ421N7nk#「排列组合」学习指南！$https://www.bilibili.com/video/BV1iA4m1P7Fu#排列组合不会做题？各类方法大梳理！$https://www.bilibili.com/video/BV1Gr421t7tr#「二项式定理」学不懂？一个视频完全搞定！$https://www.bilibili.com/video/BV1hEwMzFEuS#【概率统计】条件概率！保姆级讲解！$https://www.bilibili.com/video/BV1TQwCzsEKP"
    }
  ]
}