{
	"code": 1,
	"msg": "数据列表",
	"page": 1,
	"pagecount": 4641,
	"limit": "20",
	"total": 92816,
	"list": [
		{
			"vod_id": 48728,
			"vod_name": "80天通关几何辅助线",
			"vod_pic": "https://gh-proxy.com/https://raw.githubusercontent.com/ysztcn/ysztcn.github.io/master/biubiu/pic/weixin.jpg",
			"vod_remarks": "69"
		},
		{
			"vod_id": 100280,
			"vod_name": "T2",
			"vod_pic": "https://gh-proxy.com/https://raw.githubusercontent.com/ysztcn/ysztcn.github.io/master/biubiu/pic/weixin.jpg",
			"vod_remarks": "更新10"
		}
	]
}